{"is_source_file": true, "format": "TypeScript/TSX", "description": "This file defines a set of React components for a customizable UI menubar, utilizing Radix UI primitives and lucide icons. It includes components for menu, group, portal, radio group, submenu, items, labels, separators, and shortcuts, with styling and forwarding refs for accessibility and flexibility.", "external_files": ["@radix-ui/react-menubar", "lucide-react", "@/lib/utils"], "external_methods": ["React.forwardRef", "React.ComponentProps", "React.ComponentPropsWithoutRef", "React.ElementRef"], "published": ["Menubar", "MenubarMenu", "MenubarTrigger", "MenubarContent", "MenubarItem", "MenubarSeparator", "MenubarLabel", "MenubarCheckboxItem", "MenubarRadioGroup", "MenubarRadioItem", "MenubarPortal", "MenubarSubContent", "MenubarSubTrigger", "MenubarGroup", "MenubarSub", "MenubarShortcut"], "classes": [], "methods": [{"name": "MenubarMenu", "description": "A wrapper component for Radix UI Menu component, passing through props."}, {"name": "MenubarGroup", "description": "A wrapper component for Radix UI Group component, passing through props."}, {"name": "MenubarPortal", "description": "A wrapper component for Radix UI Portal component, passing through props."}, {"name": "MenubarRadioGroup", "description": "A wrapper component for Radix UI RadioGroup, passing through props."}, {"name": "MenubarSub", "description": "A wrapper component for Radix UI Sub component, adding a data-slot attribute."}, {"name": "Menubar", "description": "Main menubar component with styling and ref forwarding."}, {"name": "MenubarTrigger", "description": "Component for the trigger button of the menubar, with styling and ref forwarding."}, {"name": "MenubarSubTrigger", "description": "Component for submenu trigger, with optional inset styling."}, {"name": "MenubarSubContent", "description": "Component for submenu content, with animated and styled container."}, {"name": "MenubarContent", "description": "Component for the main menu content, with portal and styling."}, {"name": "MenubarItem", "description": "A menu item component with styling and optional inset."}, {"name": "MenubarCheckboxItem", "description": "Checkbox menu item with indicator icon."}, {"name": "MenubarRadioItem", "description": "Radio button menu item with indicator icon."}, {"name": "MenubarLabel", "description": "Label component for menu sections."}, {"name": "MenubarSeparator", "description": "Separator line component for menu separation."}, {"name": "MenubarShortcut", "description": "Component for displaying shortcut hints in menu items."}], "calls": ["React.forwardRef", "cn", "MenubarPrimitive.Menu", "MenubarPrimitive.Group", "MenubarPrimitive.Portal", "MenubarPrimitive.RadioGroup", "MenubarPrimitive.Sub", "MenubarPrimitive.Root", "MenubarPrimitive.Trigger", "MenubarPrimitive.SubTrigger", "MenubarPrimitive.SubContent", "MenubarPrimitive.Content", "MenubarPrimitive.Item", "MenubarPrimitive.CheckboxItem", "MenubarPrimitive.RadioItem", "MenubarPrimitive.Label", "MenubarPrimitive.Separator"], "search-terms": ["react menubar components", "radix-ui react menubar", "custom React menubar", "typescript menubar", "ui menu components"], "state": 2, "file_id": 38, "knowledge_revision": 125, "git_revision": "5cfa8019f677698d3745ad987f8c25ebb5a0028e", "ctags": [], "filename": "src/components/ui/menubar.tsx", "hash": "58cf7fc18611a53a35131555279c211b", "format-version": 4, "code-base-name": "https://github.com/MalaiarasuGRaj/jira-integration-firebase.git:main", "revision_history": [{"125": "5cfa8019f677698d3745ad987f8c25ebb5a0028e"}]}